{
	"hamza": {
		"email": "hamza@rastera.xyz",
		"name": "Hamza Sayed-Ali"
	},
	"minya": {
		"email": "minya@rastera.xyz",
		"name": "Minya Bai"
	},
	"eric": {
		"email": "eric@rastera.xyz",
		"name": "Eric Yu"
	},
	"rahma": {
		"email": "rahma@rastera.xyz",
		"name": "Rahma Gillan"
	},
	"erik": {
		"email": "erik@rastera.xyz",
		"name": "Erik Yzeiri"
	},
	"anita": {
		"email": "anita@rastera.xyz",
		"name": "Anita Hu"
	},
	"tiffany": {
		"email": "tiffany@rastera.xyz",
		"name": "Tiffany Lin"
	},
	"jenny": {
		"email": "jenny@rastera.xyz",
		"name": "Jenny chen"
	},
	"keith": {
		"email": "keith@rastera.xyz",
		"name": "Keith Wong"
	},
	"tailai": {
		"email": "tailai@rastera.xyz",
		"name": "Tailai Wang"
	},
	"albert": {
		"email": "albert@rastera.xyz",
		"name": "Albert Zhan"
	},
	"qin": {
		"email": "qin@rastera.xyz",
		"name": "Qin Liu"
	},
	"noor": {
		"email": "noor@rastera.xyz",
		"name": "Noor Nasri"
	},
	"aaron": {
		"email": "aaron@rastera.xyz",
		"name": "Aaron Li"
	}
}
