{
	"jerry": {
		"email": "jerry@masseyhacks.ca",
		"name": "Jerry Chen",
		"developer" : false,
		"reviewer" : true
	},
	"doris": {
		"email": "doris@masseyhacks.ca",
		"name": "Doris Chang",
		"developer" : false,
		"reviewer" : true
	},
	"henry": {
		"email": "henry@masseyhacks.ca",
		"name": "Henry Tu",
		"developer" : true,
		"reviewer" : false
	},
	"you": {
		"email": "you@masseyhacks.ca",
		"name": "You Zhou",
		"developer" : true,
		"reviewer" : false
	},
	"ryan": {
		"email": "ryan@masseyhacks.ca",
		"name": "Ryan Zhang",
		"developer" : true,
		"reviewer" : false
	}
}